depspy/__init__.py
depspy/client.py
depspy/exceptions.py
depspy/models.py
depspy/version.py
depspy-1.3.2.dist-info/LICENSE
depspy-1.3.2.dist-info/METADATA
depspy-1.3.2.dist-info/WHEEL
depspy-1.3.2.dist-info/top_level.txt
depspy-1.3.2.dist-info/RECORD
