Metadata-Version: 2.1
Name: depspy
Version: 1.3.2
Summary: Асинхронная библиотека для работы с Deps API
Home-page: https://github.com/fakelag28/DepsPy
Author: fakelag28
Classifier: Programming Language :: Python :: 3
Classifier: License :: OSI Approved :: MIT License
Classifier: Operating System :: OS Independent
Requires-Python: >=3.8
License-File: LICENSE
Requires-Dist: aiohttp>=3.8.0
Requires-Dist: pydantic>=2.0.0
